MANIFEST.in
README.md
VERSION
requirements.txt
setup.py
datamountaineer/__init__.py
datamountaineer/schemaregistry/__init__.py
datamountaineer/schemaregistry/client/ClientError.py
datamountaineer/schemaregistry/client/SchemaRegistryClient.py
datamountaineer/schemaregistry/client/__init__.py
datamountaineer/schemaregistry/serializers/MessageSerializer.py
datamountaineer/schemaregistry/serializers/Util.py
datamountaineer/schemaregistry/serializers/__init__.py
datamountaineer/schemaregistry/tests/__init__.py
datamountaineer/schemaregistry/tests/adv_schema.avsc
datamountaineer/schemaregistry/tests/basic_schema.avsc
datamountaineer/schemaregistry/tests/data_gen.py
datamountaineer/schemaregistry/tests/mock_registry.py
datamountaineer/schemaregistry/tests/test_cached_client.py
datamountaineer/schemaregistry/tests/test_message_serializer.py
datamountaineer/schemaregistry/tests/test_registry.py
datamountaineer/schemaregistry/tests/test_util.py
datamountaineer_schemaregistry.egg-info/PKG-INFO
datamountaineer_schemaregistry.egg-info/SOURCES.txt
datamountaineer_schemaregistry.egg-info/dependency_links.txt
datamountaineer_schemaregistry.egg-info/requires.txt
datamountaineer_schemaregistry.egg-info/top_level.txt