Metadata-Version: 1.1
Name: datamountaineer-schemaregistry
Version: 0.3
Summary: DataMountaineer Python 3 Confluent Schema Registry Client
Home-page: https://github.com/datamountaineer/python-serializers
Author: DataMountaineer
Author-email: andrew@datamountaineer.com
License: Apache 2.0
Keywords: datamountaineer schema registry schemaregistry confluent avro
Platform: UNKNOWN
Classifier: Development Status :: 4 - Beta
Classifier: Intended Audience :: Developers
Classifier: License :: OSI Approved :: Apache Software License
Classifier: Operating System :: OS Independent
Classifier: Programming Language :: Python
Classifier: Topic :: Software Development :: Libraries
